Workbook

Sheet Summary
A1: CoreStack AWS Onboarding - FinOps Bundle with Bedrock & AI Observability: IAM Permission Summary
A2: Source: AWS_Onboarding_FinopsBundle_WithBedrockWithAIObs_Final.json. Access levels: AWS Service Authorization Reference (iam-dataset, retrieved 2026-09-28).
A4: Metric | B4: Count
A5: Total permission entries in CFN (as written) | B5: =COUNTA(Permissions!$G$5:$G$284)
A6: - Specific actions | B6: =COUNTIF(Permissions!$H$5:$H$284,"Specific")
A7: - Wildcard entries | B7: =COUNTIF(Permissions!$H$5:$H$284,"Wildcard")
A8: Entries classified Read | B8: =COUNTIF(Permissions!$K$5:$K$284,"Read")
A9: Entries classified Read + Write (mixed wildcard) | B9: =COUNTIF(Permissions!$K$5:$K$284,"Read + Write (mixed)")
A10: Entries classified Write | B10: =COUNTIF(Permissions!$K$5:$K$284,"Write")
A11: Invalid entries (grant nothing) | B11: =COUNTIF(Permissions!$K$5:$K$284,"Invalid*")
A12: Entries with duplicates across policies | B12: =COUNTIF(Permissions!$R$5:$R$284,"*DUPLICATE*")
A13: High sensitivity entries | B13: =COUNTIF(Permissions!$O$5:$O$284,"High")
A14: Medium sensitivity entries | B14: =COUNTIF(Permissions!$O$5:$O$284,"Medium")
A15: Concrete actions after wildcard expansion (incl. duplicates) | B15: =COUNTA('Wildcard Expansion'!$E$5:$E$1808)
A16: - Concrete actions AWS classifies Read/List | B16: =COUNTIF('Wildcard Expansion'!$H$5:$H$1808,"Read")
A17: - Concrete actions AWS classifies Write / Permissions mgmt | B17: =COUNTIF('Wildcard Expansion'!$H$5:$H$1808,"Write")
A18: - Concrete actions unclassified by AWS | B18: =COUNTIF('Wildcard Expansion'!$H$5:$H$1808,"Unclassified")
A20: IAM Policy | B20: Attached When | C20: Entries | D20: Read | E20: Mixed / Write | F20: Invalid | G20: High Sensitivity
A21: CoreStack_BudgetAndBillingPolicy | B21: Always attached | C21: =COUNTIF(Permissions!$C$5:$C$284,A21) | D21: =COUNTIFS(Permissions!$C$5:$C$284,A21,Permissions!$K$5:$K$284,"Read") | E21: =COUNTIFS(Permissions!$C$5:$C$284,A21,Permissions!$K$5:$K$284,"*Write*") | F21: =COUNTIFS(Permissions!$C$5:$C$284,A21,Permissions!$K$5:$K$284,"Invalid*") | G21: =COUNTIFS(Permissions!$C$5:$C$284,A21,Permissions!$O$5:$O$284,"High")
A22: CoreStack_SupportAndRIPolicy | B22: Always attached | C22: =COUNTIF(Permissions!$C$5:$C$284,A22) | D22: =COUNTIFS(Permissions!$C$5:$C$284,A22,Permissions!$K$5:$K$284,"Read") | E22: =COUNTIFS(Permissions!$C$5:$C$284,A22,Permissions!$K$5:$K$284,"*Write*") | F22: =COUNTIFS(Permissions!$C$5:$C$284,A22,Permissions!$K$5:$K$284,"Invalid*") | G22: =COUNTIFS(Permissions!$C$5:$C$284,A22,Permissions!$O$5:$O$284,"High")
A23: CoreStack_AWSCURAccessPolicy | B23: Only if AWSCostAndUsageReportCURBucketName is provided | C23: =COUNTIF(Permissions!$C$5:$C$284,A23) | D23: =COUNTIFS(Permissions!$C$5:$C$284,A23,Permissions!$K$5:$K$284,"Read") | E23: =COUNTIFS(Permissions!$C$5:$C$284,A23,Permissions!$K$5:$K$284,"*Write*") | F23: =COUNTIFS(Permissions!$C$5:$C$284,A23,Permissions!$K$5:$K$284,"Invalid*") | G23: =COUNTIFS(Permissions!$C$5:$C$284,A23,Permissions!$O$5:$O$284,"High")
A24: CoreStack_ComputeOptimizerPolicy | B24: Always attached | C24: =COUNTIF(Permissions!$C$5:$C$284,A24) | D24: =COUNTIFS(Permissions!$C$5:$C$284,A24,Permissions!$K$5:$K$284,"Read") | E24: =COUNTIFS(Permissions!$C$5:$C$284,A24,Permissions!$K$5:$K$284,"*Write*") | F24: =COUNTIFS(Permissions!$C$5:$C$284,A24,Permissions!$K$5:$K$284,"Invalid*") | G24: =COUNTIFS(Permissions!$C$5:$C$284,A24,Permissions!$O$5:$O$284,"High")
A25: CoreStack_InventoryFinopsReadPolicy | B25: Always attached | C25: =COUNTIF(Permissions!$C$5:$C$284,A25) | D25: =COUNTIFS(Permissions!$C$5:$C$284,A25,Permissions!$K$5:$K$284,"Read") | E25: =COUNTIFS(Permissions!$C$5:$C$284,A25,Permissions!$K$5:$K$284,"*Write*") | F25: =COUNTIFS(Permissions!$C$5:$C$284,A25,Permissions!$K$5:$K$284,"Invalid*") | G25: =COUNTIFS(Permissions!$C$5:$C$284,A25,Permissions!$O$5:$O$284,"High")
A26: CoreStack_S3CostOptimizationPolicy | B26: Only if EnableS3CostSavingsRecommendation = true | C26: =COUNTIF(Permissions!$C$5:$C$284,A26) | D26: =COUNTIFS(Permissions!$C$5:$C$284,A26,Permissions!$K$5:$K$284,"Read") | E26: =COUNTIFS(Permissions!$C$5:$C$284,A26,Permissions!$K$5:$K$284,"*Write*") | F26: =COUNTIFS(Permissions!$C$5:$C$284,A26,Permissions!$K$5:$K$284,"Invalid*") | G26: =COUNTIFS(Permissions!$C$5:$C$284,A26,Permissions!$O$5:$O$284,"High")
A27: CoreStack_BedrockPermissions_Listing | B27: Only if EnableBedrockPermissions = true | C27: =COUNTIF(Permissions!$C$5:$C$284,A27) | D27: =COUNTIFS(Permissions!$C$5:$C$284,A27,Permissions!$K$5:$K$284,"Read") | E27: =COUNTIFS(Permissions!$C$5:$C$284,A27,Permissions!$K$5:$K$284,"*Write*") | F27: =COUNTIFS(Permissions!$C$5:$C$284,A27,Permissions!$K$5:$K$284,"Invalid*") | G27: =COUNTIFS(Permissions!$C$5:$C$284,A27,Permissions!$O$5:$O$284,"High")
A28: CoreStack_BedrockPermissions_DeepGet | B28: Only if EnableBedrockPermissions = true | C28: =COUNTIF(Permissions!$C$5:$C$284,A28) | D28: =COUNTIFS(Permissions!$C$5:$C$284,A28,Permissions!$K$5:$K$284,"Read") | E28: =COUNTIFS(Permissions!$C$5:$C$284,A28,Permissions!$K$5:$K$284,"*Write*") | F28: =COUNTIFS(Permissions!$C$5:$C$284,A28,Permissions!$K$5:$K$284,"Invalid*") | G28: =COUNTIFS(Permissions!$C$5:$C$284,A28,Permissions!$O$5:$O$284,"High")
A29: CoreStack_BedrockPermissions_TagRead | B29: Only if EnableBedrockPermissions = true | C29: =COUNTIF(Permissions!$C$5:$C$284,A29) | D29: =COUNTIFS(Permissions!$C$5:$C$284,A29,Permissions!$K$5:$K$284,"Read") | E29: =COUNTIFS(Permissions!$C$5:$C$284,A29,Permissions!$K$5:$K$284,"*Write*") | F29: =COUNTIFS(Permissions!$C$5:$C$284,A29,Permissions!$K$5:$K$284,"Invalid*") | G29: =COUNTIFS(Permissions!$C$5:$C$284,A29,Permissions!$O$5:$O$284,"High")
A30: CoreStack_FinOpsForAI_Bedrock | B30: Only if EnableFinOpsForAI = true | C30: =COUNTIF(Permissions!$C$5:$C$284,A30) | D30: =COUNTIFS(Permissions!$C$5:$C$284,A30,Permissions!$K$5:$K$284,"Read") | E30: =COUNTIFS(Permissions!$C$5:$C$284,A30,Permissions!$K$5:$K$284,"*Write*") | F30: =COUNTIFS(Permissions!$C$5:$C$284,A30,Permissions!$K$5:$K$284,"Invalid*") | G30: =COUNTIFS(Permissions!$C$5:$C$284,A30,Permissions!$O$5:$O$284,"High")
A31: CoreStack_FinOpsForAI_CloudWatchLogs | B31: Only if EnableFinOpsForAI = true | C31: =COUNTIF(Permissions!$C$5:$C$284,A31) | D31: =COUNTIFS(Permissions!$C$5:$C$284,A31,Permissions!$K$5:$K$284,"Read") | E31: =COUNTIFS(Permissions!$C$5:$C$284,A31,Permissions!$K$5:$K$284,"*Write*") | F31: =COUNTIFS(Permissions!$C$5:$C$284,A31,Permissions!$K$5:$K$284,"Invalid*") | G31: =COUNTIFS(Permissions!$C$5:$C$284,A31,Permissions!$O$5:$O$284,"High")
A32: CoreStack_FinOpsForAI_IAM | B32: Only if EnableFinOpsForAI = true | C32: =COUNTIF(Permissions!$C$5:$C$284,A32) | D32: =COUNTIFS(Permissions!$C$5:$C$284,A32,Permissions!$K$5:$K$284,"Read") | E32: =COUNTIFS(Permissions!$C$5:$C$284,A32,Permissions!$K$5:$K$284,"*Write*") | F32: =COUNTIFS(Permissions!$C$5:$C$284,A32,Permissions!$K$5:$K$284,"Invalid*") | G32: =COUNTIFS(Permissions!$C$5:$C$284,A32,Permissions!$O$5:$O$284,"High")
A33: CoreStack_FinOpsForAI_APIGateway | B33: Only if EnableFinOpsForAI = true | C33: =COUNTIF(Permissions!$C$5:$C$284,A33) | D33: =COUNTIFS(Permissions!$C$5:$C$284,A33,Permissions!$K$5:$K$284,"Read") | E33: =COUNTIFS(Permissions!$C$5:$C$284,A33,Permissions!$K$5:$K$284,"*Write*") | F33: =COUNTIFS(Permissions!$C$5:$C$284,A33,Permissions!$K$5:$K$284,"Invalid*") | G33: =COUNTIFS(Permissions!$C$5:$C$284,A33,Permissions!$O$5:$O$284,"High")
A34: TOTAL | C34: =SUM(C21:C33) | D34: =SUM(D21:D33) | E34: =SUM(E21:E33) | F34: =SUM(F21:F33) | G34: =SUM(G21:G33)
A36: Legend
A37: Read | B37: AWS access level 'Read' or 'List' - returns data/metadata, makes no change.
A38: Write | B38: AWS access level 'Write' or 'Permissions management' (AWS's metadata label). A label only - see the 'Actual Behaviour' column and 'Access Level Guide' sheet for what the API really does.
A39: Read + Write (mixed) | B39: Wildcard whose expansion includes both Read/List and AWS-classified Write actions.
A40: Invalid - no effect | B40: Action/service prefix does not exist in AWS; grants nothing.
A41: Sensitivity High / Medium / Low | B41: CoreStack review rating of data exposure or side effects (see notes).
A42: Sheets | B42: Permissions = one row per CFN permission with purpose; Wildcard Expansion = every concrete action; Write & Sensitive = items needing attention; Findings = review observations; Role, Trust & Parameters = trust policy and conditions.

Sheet Permissions
A1: CoreStack FinOps Bundle (with Bedrock & AI Observability) - IAM Permission Register
A2: One row per permission exactly as written in the CloudFormation template. Access levels per AWS Service Authorization Reference.
A4: S.No | B4: CFN Resource | C4: IAM Policy Name | D4: FinOps Feature Area | E4: Attached When (CFN Condition) | F4: AWS Service | G4: Permission (as written in CFN) | H4: Specific / Wildcard | I4: # Actions Covered | J4: AWS Access Level (official) | K4: Read / Write | L4: Resource Scope | M4: What the permission does (AWS definition) | N4: Why CoreStack uses it | O4: Sensitivity | P4: Sensitivity / Risk Notes | Q4: Modifies Customer Resources / State? | R4: Validity / Remarks
A5: 1 | B5: BudgetAndBillingPolicy | C5: CoreStack_BudgetAndBillingPolicy | D5: Budgets & Billing | E5: Always attached | F5: AWS Budget Service | G5: budgets:ViewBudget | H5: Specific | I5: 1 | J5: Read | K5: Read | L5: All resources (*) | M5: Grants permission to view budgets and budget details | N5: Reads the customer's AWS Budgets (limits, actual vs forecasted spend, thresholds) so CoreStack can show budget burn-down, variance and alerts on the FinOps budget dashboards. | O5: Low | P5: Metadata / configuration only. | Q5: No | R5: Valid
A6: 2 | B6: BudgetAndBillingPolicy | C6: CoreStack_BudgetAndBillingPolicy | D6: Budgets & Billing | E6: Always attached | F6: AWS Budget Service | G6: budgets:DescribeBudgetActionHistories | H6: Specific | I6: 1 | J6: Read | K6: Read | L6: All resources (*) | M6: Grants permission to retrieve a historical view of the budget actions statuses associated with a particular budget action. These status include statues such as 'Standby', 'Pending' and 'Executed' | N6: Reads the history of automated budget actions (e.g. SCP/IAM policy applied when a budget was breached) to display budget-enforcement audit trail in CoreStack. | O6: Low | P6: Metadata / configuration only. | Q6: No | R6: Valid
A7: 3 | B7: BudgetAndBillingPolicy | C7: CoreStack_BudgetAndBillingPolicy | D7: Budgets & Billing | E7: Always attached | F7: AWS Budget Service | G7: budgets:DescribeBudgetActionsForAccount | H7: Specific | I7: 1 | J7: Read | K7: Read | L7: All resources (*) | M7: Grants permission to retrieve the details of all of the budget actions associated with your account | N7: Lists budget actions configured in the account so CoreStack can show which budgets have automated guardrails attached. | O7: Low | P7: Metadata / configuration only. | Q7: No | R7: Valid
A8: 4 | B8: SupportAndRIPolicy | C8: CoreStack_SupportAndRIPolicy | D8: Commitments (RI) & Trusted Advisor | E8: Always attached | F8: AWS Cost Explorer Service | G8: ce:GetReservationPurchaseRecommendation | H8: Specific | I8: 1 | J8: Read | K8: Read | L8: All resources (*) | M8: Grants permission to retrieve the reservation recommendations for your account | N8: Fetches AWS Cost Explorer Reserved Instance purchase recommendations (EC2, RDS, ElastiCache, Redshift, OpenSearch) to populate CoreStack's RI commitment-savings recommendations. | O8: Low | P8: Metadata / configuration only. | Q8: No | R8: Valid
A9: 5 | B9: SupportAndRIPolicy | C9: CoreStack_SupportAndRIPolicy | D9: Commitments (RI) & Trusted Advisor | E9: Always attached | F9: AWS Cost Explorer Service | G9: ce:GetReservationUtilization | H9: Specific | I9: 1 | J9: Read | K9: Read | L9: All resources (*) | M9: Grants permission to retrieve the reservation utilization for your account | N9: Reads how much of the purchased Reserved Instances are actually used, to report RI utilization and flag under-utilized (wasted) reservations. | O9: Low | P9: Metadata / configuration only. | Q9: No | R9: Valid
A10: 6 | B10: SupportAndRIPolicy | C10: CoreStack_SupportAndRIPolicy | D10: Commitments (RI) & Trusted Advisor | E10: Always attached | F10: AWS Cost Explorer Service | G10: ce:DescribeNotificationSubscription | H10: Specific | I10: 1 | J10: Read | K10: Read | L10: All resources (*) | M10: Grants permission to view Reservation expiration alerts | N10: Reads Cost Anomaly Detection notification subscriptions so CoreStack can show which anomaly monitors/alerts are configured. | O10: Low | P10: Metadata / configuration only. | Q10: No | R10: Valid
A11: 7 | B11: SupportAndRIPolicy | C11: CoreStack_SupportAndRIPolicy | D11: Commitments (RI) & Trusted Advisor | E11: Always attached | F11: AWS Cost Explorer Service | G11: ce:GetReservationCoverage | H11: Specific | I11: 1 | J11: Read | K11: Read | L11: All resources (*) | M11: Grants permission to retrieve the reservation coverage for your account | N11: Reads what percentage of eligible usage is covered by RIs, to report RI coverage and identify on-demand spend that could be covered by commitments. | O11: Low | P11: Metadata / configuration only. | Q11: No | R11: Valid
A12: 8 | B12: SupportAndRIPolicy | C12: CoreStack_SupportAndRIPolicy | D12: Commitments (RI) & Trusted Advisor | E12: Always attached | F12: AWS Support | G12: support:DescribeServices | H12: Specific | I12: 1 | J12: Read | K12: Read | L12: All resources (*) | M12: Grants permission to list AWS services and categories that applies to each service | N12: Lists AWS services/categories known to AWS Support; required context for reading Trusted Advisor results. | O12: Low | P12: Metadata / configuration only. | Q12: No | R12: Valid
A13: 9 | B13: SupportAndRIPolicy | C13: CoreStack_SupportAndRIPolicy | D13: Commitments (RI) & Trusted Advisor | E13: Always attached | F13: AWS Support | G13: support:DescribeSupportLevel | H13: Specific | I13: 1 | J13: Read | K13: Read | L13: All resources (*) | M13: Grants permission to return the support level for an AWS Account identifier | N13: Reads the account's AWS Support plan (Basic/Developer/Business/Enterprise) to know whether full Trusted Advisor cost-optimization checks are available. | O13: Low | P13: Metadata / configuration only. | Q13: No | R13: Valid
A14: 10 | B14: SupportAndRIPolicy | C14: CoreStack_SupportAndRIPolicy | D14: Commitments (RI) & Trusted Advisor | E14: Always attached | F14: AWS Support | G14: support:DescribeTrustedAdvisorCheckResult | H14: Specific | I14: 1 | J14: Read | K14: Read | L14: All resources (*) | M14: Grants permission to get the results of the Trusted Advisor check that has the specified check identifier | N14: Reads Trusted Advisor check results (e.g. idle load balancers, underutilized EC2, unassociated Elastic IPs, low-utilization EBS) that CoreStack ingests as cost-saving recommendations. | O14: Low | P14: Metadata / configuration only. | Q14: No | R14: Valid
A15: 11 | B15: SupportAndRIPolicy | C15: CoreStack_SupportAndRIPolicy | D15: Commitments (RI) & Trusted Advisor | E15: Always attached | F15: AWS Support | G15: support:DescribeTrustedAdvisorChecks | H15: Specific | I15: 1 | J15: Read | K15: Read | L15: All resources (*) | M15: Grants permission to get a list of all available Trusted Advisor checks, including name, identifier, category and description | N15: Lists the available Trusted Advisor checks (IDs, categories) so CoreStack knows which cost-optimization check results to fetch. | O15: Low | P15: Metadata / configuration only. | Q15: No | R15: Valid
A16: 12 | B16: AWSCURAccessPolicy | C16: CoreStack_AWSCURAccessPolicy | D16: Cost & Usage Report ingestion | E16: Only if AWSCostAndUsageReportCURBucketName is provided | F16: Amazon S3 | G16: s3:GetObject | H16: Specific | I16: 1 | J16: Read | K16: Read | L16: arn:aws:s3:::<AWSCostAndUsageReportCURBucketName>/* (CUR bucket objects only) | M16: Grants permission to retrieve objects from Amazon S3 | N16: Downloads the Cost and Usage Report (CUR) files from the customer's CUR S3 bucket ONLY (resource is scoped to arn:aws:s3:::<CURBucket>/*). CUR is the primary source of billing line-items for all cost reporting, chargeback/showback and allocation in CoreStack. | O16: Medium | P16: Reads object content - scoped only to the CUR bucket. | Q16: No | R16: Valid
... A284: 280 | B284: FinOpsForAIAPIGatewayPolicy | C284: CoreStack_FinOpsForAI_APIGateway | D284: FinOps for AI - Gateway Integration | E284: Only if EnableFinOpsForAI = true | F284: Amazon API Gateway Management | G284: apigateway:GET | H284: Specific | I284: 1 | J284: Read | K284: Read | L284: All resources (*) | M284: Grants permission to read a particular resource | N284: Read-only access to all API Gateway GET endpoints (REST/HTTP/WebSocket APIs, stages, usage plans, tags). Used to inventory APIs, stages and caches (API cache is billable) and to read tags for cost allocation. For FinOps for AI it also discovers API Gateways fronting LLM/Bedrock backends (Gateway Integration). | O284: Medium | P284: Includes GET on /apikeys?includeValues=true which can return API key values. | Q284: No | R284: DUPLICATE - also granted in CoreStack_InventoryFinopsReadPolicy

Sheet Wildcard Expansion
A1: Every concrete AWS action granted (all wildcards expanded)
A2: Wildcards (e.g. ec2:Describe*) are expanded to each individual action they grant today. New AWS actions matching a wildcard are granted automatically in future.
A4: S.No | B4: IAM Policy Name | C4: Attached When | D4: Permission in CFN | E4: Concrete Action Granted | F4: AWS Service | G4: AWS Access Level (AWS label) | H4: Read / Write (per AWS label) | I4: AWS Description | J4: Sensitivity | K4: Notes | L4: Actual Behaviour (what the API really does)
A5: 1 | B5: CoreStack_BudgetAndBillingPolicy | C5: Always attached | D5: budgets:ViewBudget | E5: budgets:ViewBudget | F5: AWS Budget Service | G5: Read | H5: Read | I5: Grants permission to view budgets and budget details | J5: Low | L5: Read-only
A6: 2 | B6: CoreStack_BudgetAndBillingPolicy | C6: Always attached | D6: budgets:DescribeBudgetActionHistories | E6: budgets:DescribeBudgetActionHistories | F6: AWS Budget Service | G6: Read | H6: Read | I6: Grants permission to retrieve a historical view of the budget actions statuses associated with a particular budget action. These status include statues such as 'Standby', 'Pending' and 'Executed' | J6: Low | L6: Read-only
A7: 3 | B7: CoreStack_BudgetAndBillingPolicy | C7: Always attached | D7: budgets:DescribeBudgetActionsForAccount | E7: budgets:DescribeBudgetActionsForAccount | F7: AWS Budget Service | G7: Read | H7: Read | I7: Grants permission to retrieve the details of all of the budget actions associated with your account | J7: Low | L7: Read-only
A8: 4 | B8: CoreStack_SupportAndRIPolicy | C8: Always attached | D8: ce:GetReservationPurchaseRecommendation | E8: ce:GetReservationPurchaseRecommendation | F8: AWS Cost Explorer Service | G8: Read | H8: Read | I8: Grants permission to retrieve the reservation recommendations for your account | J8: Low | L8: Read-only
A9: 5 | B9: CoreStack_SupportAndRIPolicy | C9: Always attached | D9: ce:GetReservationUtilization | E9: ce:GetReservationUtilization | F9: AWS Cost Explorer Service | G9: Read | H9: Read | I9: Grants permission to retrieve the reservation utilization for your account | J9: Low | L9: Read-only
A10: 6 | B10: CoreStack_SupportAndRIPolicy | C10: Always attached | D10: ce:DescribeNotificationSubscription | E10: ce:DescribeNotificationSubscription | F10: AWS Cost Explorer Service | G10: Read | H10: Read | I10: Grants permission to view Reservation expiration alerts | J10: Low | L10: Read-only
A11: 7 | B11: CoreStack_SupportAndRIPolicy | C11: Always attached | D11: ce:GetReservationCoverage | E11: ce:GetReservationCoverage | F11: AWS Cost Explorer Service | G11: Read | H11: Read | I11: Grants permission to retrieve the reservation coverage for your account | J11: Low | L11: Read-only
A12: 8 | B12: CoreStack_SupportAndRIPolicy | C12: Always attached | D12: support:DescribeServices | E12: support:DescribeServices | F12: AWS Support | G12: Read | H12: Read | I12: Grants permission to list AWS services and categories that applies to each service | J12: Low | L12: Read-only
A13: 9 | B13: CoreStack_SupportAndRIPolicy | C13: Always attached | D13: support:DescribeSupportLevel | E13: support:DescribeSupportLevel | F13: AWS Support | G13: Read | H13: Read | I13: Grants permission to return the support level for an AWS Account identifier | J13: Low | L13: Read-only
A14: 10 | B14: CoreStack_SupportAndRIPolicy | C14: Always attached | D14: support:DescribeTrustedAdvisorCheckResult | E14: support:DescribeTrustedAdvisorCheckResult | F14: AWS Support | G14: Read | H14: Read | I14: Grants permission to get the results of the Trusted Advisor check that has the specified check identifier | J14: Low | L14: Read-only
A15: 11 | B15: CoreStack_SupportAndRIPolicy | C15: Always attached | D15: support:DescribeTrustedAdvisorChecks | E15: support:DescribeTrustedAdvisorChecks | F15: AWS Support | G15: Read | H15: Read | I15: Grants permission to get a list of all available Trusted Advisor checks, including name, identifier, category and description | J15: Low | L15: Read-only
A16: 12 | B16: CoreStack_AWSCURAccessPolicy | C16: Only if AWSCostAndUsageReportCURBucketName is provided | D16: s3:GetObject | E16: s3:GetObject | F16: Amazon S3 | G16: Read | H16: Read | I16: Grants permission to retrieve objects from Amazon S3 | J16: Medium | K16: Reads object content - scoped only to the CUR bucket. | L16: Read-only
A17: 13 | B17: CoreStack_ComputeOptimizerPolicy | C17: Always attached | D17: compute-optimizer:DescribeRecommendationExportJobs | E17: compute-optimizer:DescribeRecommendationExportJobs | F17: AWS Compute Optimizer | G17: List | H17: Read | I17: Grants permission to view the status of recommendation export jobs | J17: Low | L17: Read-only
A18: 14 | B18: CoreStack_ComputeOptimizerPolicy | C18: Always attached | D18: compute-optimizer:GetAutoScalingGroupRecommendations | E18: compute-optimizer:GetAutoScalingGroupRecommendations | F18: AWS Compute Optimizer | G18: List | H18: Read | I18: Grants permission to get recommendations for the provided AutoScaling groups | J18: Low | L18: Read-only
A19: 15 | B19: CoreStack_ComputeOptimizerPolicy | C19: Always attached | D19: compute-optimizer:GetEBSVolumeRecommendations | E19: compute-optimizer:GetEBSVolumeRecommendations | F19: AWS Compute Optimizer | G19: List | H19: Read | I19: Grants permission to get recommendations for the provided EBS volumes | J19: Low | L19: Read-only
A20: 16 | B20: CoreStack_ComputeOptimizerPolicy | C20: Always attached | D20: compute-optimizer:GetEC2InstanceRecommendations | E20: compute-optimizer:GetEC2InstanceRecommendations | F20: AWS Compute Optimizer | G20: List | H20: Read | I20: Grants permission to get recommendations for the provided EC2 instances | J20: Low | L20: Read-only
A21: 17 | B21: CoreStack_ComputeOptimizerPolicy | C21: Always attached | D21: compute-optimizer:GetEC2RecommendationProjectedMetrics | E21: compute-optimizer:GetEC2RecommendationProjectedMetrics | F21: AWS Compute Optimizer | G21: List | H21: Read | I21: Grants permission to get the recommendation projected metrics of the specified instance | J21: Low | L21: Read-only
A22: 18 | B22: CoreStack_ComputeOptimizerPolicy | C22: Always attached | D22: compute-optimizer:GetECSServiceRecommendationProjectedMetrics | E22: compute-optimizer:GetECSServiceRecommendationProjectedMetrics | F22: AWS Compute Optimizer | G22: List | H22: Read | I22: Grants permission to get the recommendation projected metrics of the specified ECS service | J22: Low | L22: Read-only
A23: 19 | B23: CoreStack_ComputeOptimizerPolicy | C23: Always attached | D23: compute-optimizer:GetECSServiceRecommendations | E23: compute-optimizer:GetECSServiceRecommendations | F23: AWS Compute Optimizer | G23: List | H23: Read | I23: Grants permission to get recommendations for the provided ECS services | J23: Low | L23: Read-only
A24: 20 | B24: CoreStack_ComputeOptimizerPolicy | C24: Always attached | D24: compute-optimizer:GetEffectiveRecommendationPreferences | E24: compute-optimizer:GetEffectiveRecommendationPreferences | F24: AWS Compute Optimizer | G24: Read | H24: Read | I24: Grants permission to get recommendation preferences that are in effect | J24: Low | L24: Read-only
A25: 21 | B25: CoreStack_ComputeOptimizerPolicy | C25: Always attached | D25: compute-optimizer:GetEnrollmentStatus | E25: compute-optimizer:GetEnrollmentStatus | F25: AWS Compute Optimizer | G25: List | H25: Read | I25: Grants permission to get the enrollment status for the specified account | J25: Low | L25: Read-only
A26: 22 | B26: CoreStack_ComputeOptimizerPolicy | C26: Always attached | D26: compute-optimizer:GetLambdaFunctionRecommendations | E26: compute-optimizer:GetLambdaFunctionRecommendations | F26: AWS Compute Optimizer | G26: List | H26: Read | I26: Grants permission to get recommendations for the provided Lambda functions | J26: Low | L26: Read-only
A27: 23 | B27: CoreStack_ComputeOptimizerPolicy | C27: Always attached | D27: compute-optimizer:GetRecommendationPreferences | E27: compute-optimizer:GetRecommendationPreferences | F27: AWS Compute Optimizer | G27: Read | H27: Read | I27: Grants permission to get recommendation preferences | J27: Low | L27: Read-only
A28: 24 | B28: CoreStack_ComputeOptimizerPolicy | C28: Always attached | D28: compute-optimizer:GetRecommendationSummaries | E28: compute-optimizer:GetRecommendationSummaries | F28: AWS Compute Optimizer | G28: List | H28: Read | I28: Grants permission to get the recommendation summaries for the specified account(s) | J28: Low | L28: Read-only
... A44: 40 | B44: CoreStack_InventoryFinopsReadPolicy | C44: Always attached | D44: acm:DescribeCertificate | E44: acm:DescribeCertificate | F44: AWS Certificate Manager | G44: Read | H44: Read | I44: Grants permission to retreive a certificates and its metadata | J44: Low | L44: Read-only
A45: 41 | B45: CoreStack_InventoryFinopsReadPolicy | C45: Always attached | D45: acm:GetCertificate | E45: acm:GetCertificate | F45: AWS Certificate Manager | G45: Read | H45: Read | I45: Grants permission to retrieve a certificate and certificate chain for a certificate ARN | J45: Low | K45: Returns public certificate/chain only; private key is never returned. | L45: Read-only
A46: 42 | B46: CoreStack_InventoryFinopsReadPolicy | C46: Always attached | D46: acm:ListCertificates | E46: acm:ListCertificates | F46: AWS Certificate Manager | G46: List | H46: Read | I46: Grants permission to retrieve a list of certificates for specific certificate parameters | J46: Low | L46: Read-only
A47: 43 | B47: CoreStack_InventoryFinopsReadPolicy | C47: Always attached | D47: acm:ListTagsForCertificate | E47: acm:ListTagsForCertificate | F47: AWS Certificate Manager | G47: Read | H47: Read | I47: Grants permission to lists the tags that have been associated with a certificate | J47: Low | L47: Read-only
A48: 44 | B48: CoreStack_InventoryFinopsReadPolicy | C48: Always attached | D48: apigateway:GET | E48: apigateway:GET | F48: Amazon API Gateway Management | G48: Read | H48: Read | I48: Grants permission to read a particular resource | J48: Medium | K48: Includes GET on /apikeys?includeValues=true which can return API key values. | L48: Read-only
A49: 45 | B49: CoreStack_InventoryFinopsReadPolicy | C49: Always attached | D49: application-autoscaling:DescribeScheduledActions | E49: application-autoscaling:DescribeScheduledActions | F49: AWS Application Auto Scaling | G49: Read | H49: Read | I49: Grants permission to describe a set of scheduled actions or all scheduled actions in the specified namespace | J49: Low | L49: Read-only
A50: 46 | B50: CoreStack_InventoryFinopsReadPolicy | C50: Always attached | D50: appstream:Describe* | E50: appstream:DescribeAppBlockBuilderAppBlockAssociations | F50: Amazon AppStream 2.0 | G50: List | H50: Read | I50: Grants permission to retrieve the associations that are associated with the specified app block builder or app block | J50: Low | L50: Read-only
A51: 47 | B51: CoreStack_InventoryFinopsReadPolicy | C51: Always attached | D51: appstream:Describe* | E51: appstream:DescribeAppBlockBuilders | F51: Amazon AppStream 2.0 | G51: List | H51: Read | I51: Grants permission to retrieve a list that describes one or more specified app block builders, if the app block builder names are provided. Otherwise, all app block builders in the account are described | J51: Low | L51: Read-only
A52: 48 | B52: CoreStack_InventoryFinopsReadPolicy | C52: Always attached | D52: appstream:Describe* | E52: appstream:DescribeAppBlocks | F52: Amazon AppStream 2.0 | G52: List | H52: Read | I52: Grants permission to retrieve a list that describes one or more specified app blocks, if the app block arns are provided. Otherwise, all app blocks in the account are described | J52: Low | L52: Read-only
A53: 49 | B53: CoreStack_InventoryFinopsReadPolicy | C53: Always attached | D53: appstream:Describe* | E53: appstream:DescribeAppLicenseUsage | F53: Amazon AppStream 2.0 | G53: List | H53: Read | I53: Grants permission to retrieve license included application usage information | J53: Low | L53: Read-only
A54: 50 | B54: CoreStack_InventoryFinopsReadPolicy | C54: Always attached | D54: appstream:Describe* | E54: appstream:DescribeApplicationFleetAssociations | F54: Amazon AppStream 2.0 | G54: List | H54: Read | I54: Grants permission to retrieve the associations that are associated with the specified application or fleet | J54: Low | L54: Read-only
A55: 51 | B55: CoreStack_InventoryFinopsReadPolicy | C55: Always attached | D55: appstream:Describe* | E55: appstream:DescribeApplications | F55: Amazon AppStream 2.0 | G55: List | H55: Read | I55: Grants permission to retrieve a list that describes one or more specified applications, if the application arns are provided. Otherwise, all applications in the account are described | J55: Low | L55: Read-only
A56: 52 | B56: CoreStack_InventoryFinopsReadPolicy | C56: Always attached | D56: appstream:Describe* | E56: appstream:DescribeDirectoryConfigs | F56: Amazon AppStream 2.0 | G56: List | H56: Read | I56: Grants permission to retrieve a list that describes one or more specified Directory Config objects for AppStream 2.0, if the names for these objects are provided. Otherwise, all Directory Config objects in the account are described. This object includes the configuration information required to join fleets and image builders to Microsoft Active Directory domains | J56: Low | L56: Read-only
A57: 53 | B57: CoreStack_InventoryFinopsReadPolicy | C57: Always attached | D57: appstream:Describe* | E57: appstream:DescribeEntitlements | F57: Amazon AppStream 2.0 | G57: List | H57: Read | I57: Grants permission to retrieve one or all entitlements for the specified stack | J57: Low | L57: Read-only
A58: 54 | B58: CoreStack_InventoryFinopsReadPolicy | C58: Always attached | D58: appstream:Describe* | E58: appstream:DescribeFleets | F58: Amazon AppStream 2.0 | G58: List | H58: Read | I58: Grants permission to retrieve a list that describes one or more specified fleets, if the fleet names are provided. Otherwise, all fleets in the account are described | J58: Low | L58: Read-only
A59: 55 | B59: CoreStack_InventoryFinopsReadPolicy | C59: Always attached | D59: appstream:Describe* | E59: appstream:DescribeImageBuilders | F59: Amazon AppStream 2.0 | G59: List | H59: Read | I59: Grants permission to retrieve a list that describes one or more specified image builders, if the image builder names are provided. Otherwise, all image builders in the account are described | J59: Low | L59: Read-only
A60: 56 | B60: CoreStack_InventoryFinopsReadPolicy | C60: Always attached | D60: appstream:Describe* | E60: appstream:DescribeImagePermissions | F60: Amazon AppStream 2.0 | G60: Read | H60: Read | I60: Grants permission to retrieve a list that describes the permissions for shared AWS account IDs on a private image that you own | J60: Low | L60: Read-only
... A125: 121 | B125: CoreStack_InventoryFinopsReadPolicy | C125: Always attached | D125: cloudformation:GetStackPolicy | E125: cloudformation:GetStackPolicy | F125: AWS CloudFormation & Cloud Control API | G125: Read | H125: Read | I125: Grants permission to return the stack policy for a specified stack | J125: Low | L125: Read-only
A126: 122 | B126: CoreStack_InventoryFinopsReadPolicy | C126: Always attached | D126: cloudformation:GetTemplate | E126: cloudformation:GetTemplate | F126: AWS CloudFormation & Cloud Control API | G126: Read | H126: Read | I126: Grants permission to return the template body for a specified stack | J126: Medium | K126: Templates can contain hard-coded parameters/secrets. | L126: Read-only
A127: 123 | B127: CoreStack_InventoryFinopsReadPolicy | C127: Always attached | D127: cloudformation:ListStackResources | E127: cloudformation:ListStackResources | F127: AWS CloudFormation & Cloud Control API | G127: List | H127: Read | I127: Grants permission to return descriptions of all resources of the specified stack | J127: Low | L127: Read-only
A128: 124 | B128: CoreStack_InventoryFinopsReadPolicy | C128: Always attached | D128: cloudformation:ListStacks | E128: cloudformation:ListStacks | F128: AWS CloudFormation & Cloud Control API | G128: List | H128: Read | I128: Grants permission to return the summary information for stacks whose status matches the specified StackStatusFilter. In combination with the DescribeStacks action, grants permission to list descriptions for stacks | J128: Low | L128: Read-only
A129: 125 | B129: CoreStack_InventoryFinopsReadPolicy | C129: Always attached | D129: cloudfront:Get* | E129: cloudfront:GetAnycastIpList | F129: Amazon CloudFront | G129: Read | H129: Read | I129: Grants permission to get an Anycast static IP list | J129: Low | L129: Read-only
A130: 126 | B130: CoreStack_InventoryFinopsReadPolicy | C130: Always attached | D130: cloudfront:Get* | E130: cloudfront:GetCachePolicy | F130: Amazon CloudFront | G130: Read | H130: Read | I130: Grants permission to get the cache policy | J130: Low | L130: Read-only
A131: 127 | B131: CoreStack_InventoryFinopsReadPolicy | C131: Always attached | D131: cloudfront:Get* | E131: cloudfront:GetCachePolicyConfig | F131: Amazon CloudFront | G131: Read | H131: Read | I131: Grants permission to get the cache policy configuration | J131: Low | L131: Read-only
A132: 128 | B132: CoreStack_InventoryFinopsReadPolicy | C132: Always attached | D132: cloudfront:Get* | E132: cloudfront:GetCloudFrontOriginAccessIdentity | F132: Amazon CloudFront | G132: Read | H132: Read | I132: Grants permission to get the information about a CloudFront origin access identity | J132: Low | L132: Read-only
A133: 129 | B133: CoreStack_InventoryFinopsReadPolicy | C133: Always attached | D133: cloudfront:Get* | E133: cloudfront:GetCloudFrontOriginAccessIdentityConfig | F133: Amazon CloudFront | G133: Read | H133: Read | I133: Grants permission to get the configuration information about a Cloudfront origin access identity | J133: Low | L133: Read-only
A134: 130 | B134: CoreStack_InventoryFinopsReadPolicy | C134: Always attached | D134: cloudfront:Get* | E134: cloudfront:GetConnectionFunction | F134: Amazon CloudFront | G134: Read | H134: Read | I134: Grants permission to get a connection function's code | J134: Low | L134: Read-only
A135: 131 | B135: CoreStack_InventoryFinopsReadPolicy | C135: Always attached | D135: cloudfront:Get* | E135: cloudfront:GetConnectionGroup | F135: Amazon CloudFront | G135: Read | H135: Read | I135: Grants permission to get information about a connection group | J135: Low | L135: Read-only
A136: 132 | B136: CoreStack_InventoryFinopsReadPolicy | C136: Always attached | D136: cloudfront:Get* | E136: cloudfront:GetConnectionGroupByRoutingEndpoint | F136: Amazon CloudFront | G136: Read | H136: Read | I136: Grants permission to get information about a connection group by the specified routing endpoint | J136: Low | L136: Read-only
A137: 133 | B137: CoreStack_InventoryFinopsReadPolicy | C137: Always attached | D137: cloudfront:Get* | E137: cloudfront:GetContinuousDeploymentPolicy | F137: Amazon CloudFront | G137: Read | H137: Read | I137: Grants permission to get the continuous-deployment policy | J137: Low | L137: Read-only
A138: 134 | B138: CoreStack_InventoryFinopsReadPolicy | C138: Always attached | D138: cloudfront:Get* | E138: cloudfront:GetContinuousDeploymentPolicyConfig | F138: Amazon CloudFront | G138: Read | H138: Read | I138: Grants permission to get the continuous-deployment policy configuration | J138: Low | L138: Read-only
... A219: 215 | B219: CoreStack_InventoryFinopsReadPolicy | C219: Always attached | D219: cognito-identity:Describe* | E219: cognito-identity:DescribeIdentityPool | F219: Amazon Cognito Identity | G219: Read | H219: Read | I219: Grants permission to get details about a particular identity pool, including the pool name, ID description, creation date, and current number of users | J219: Low | L219: Read-only
A220: 216 | B220: CoreStack_InventoryFinopsReadPolicy | C220: Always attached | D220: cognito-identity:Get* | E220: cognito-identity:GetCredentialsForIdentity | F220: Amazon Cognito Identity | G220: Read | H220: Read | I220: Grants permission to return credentials for the provided identity ID | J220: High | K220: Returns AWS credentials for a Cognito identity. | L220: Read, but issues tokens/credentials
A221: 217 | B221: CoreStack_InventoryFinopsReadPolicy | C221: Always attached | D221: cognito-identity:Get* | E221: cognito-identity:GetId | F221: Amazon Cognito Identity | G221: Permissions management | H221: Write | I221: Grants permission to generate (or retrieve) a Cognito ID. Supplying multiple logins will create an implicit linked account | J221: Medium | K221: Creates/returns a Cognito identity ID (AWS classifies as Permissions management) - can create a new identity in the pool. | L221: Real write - can create a new identity in a Cognito identity pool
A222: 218 | B222: CoreStack_InventoryFinopsReadPolicy | C222: Always attached | D222: cognito-identity:Get* | E222: cognito-identity:GetIdentityPoolAnalytics | F222: Amazon Cognito Identity | G222: Read | H222: Read | I222: Grants permission to get analytics data about the total current identity count for all identity pool identity provider (IdPs) | J222: Low | L222: Read-only
A223: 219 | B223: CoreStack_InventoryFinopsReadPolicy | C223: Always attached | D223: cognito-identity:Get* | E223: cognito-identity:GetIdentityPoolDailyAnalytics | F223: Amazon Cognito Identity | G223: Read | H223: Read | I223: Grants permission to get analytics data about the number of new identities and total identities for all identity pool identity providers (IdPs) | J223: Low | L223: Read-only
A224: 220 | B224: CoreStack_InventoryFinopsReadPolicy | C224: Always attached | D224: cognito-identity:Get* | E224: cognito-identity:GetIdentityPoolRoles | F224: Amazon Cognito Identity | G224: Read | H224: Read | I224: Grants permission to get the roles for an identity pool | J224: Low | L224: Read-only
A225: 221 | B225: CoreStack_InventoryFinopsReadPolicy | C225: Always attached | D225: cognito-identity:Get* | E225: cognito-identity:GetIdentityProviderDailyAnalytics | F225: Amazon Cognito Identity | G225: Read | H225: Read | I225: Grants permission to get analytics data about the number of new identities and total identities for one identity pool identity provider (IdPs) | J225: Low | L225: Read-only
A226: 222 | B226: CoreStack_InventoryFinopsReadPolicy | C226: Always attached | D226: cognito-identity:Get* | E226: cognito-identity:GetOpenIdToken | F226: Amazon Cognito Identity | G226: Read | H226: Read | I226: Grants permission to get an OpenID token, using a known Cognito ID | J226: Medium | K226: Returns an OpenID token for a Cognito identity. | L226: Read, but issues tokens/credentials
A227: 223 | B227: CoreStack_InventoryFinopsReadPolicy | C227: Always attached | D227: cognito-identity:Get* | E227: cognito-identity:GetOpenIdTokenForDeveloperIdentity | F227: Amazon Cognito Identity | G227: Read | H227: Read | I227: Grants permission to register (or retrieve) a Cognito IdentityId and an OpenID Connect token for a user authenticated by your backend authentication process | J227: Medium | K227: Registers/returns an OpenID token for a developer identity. | L227: Read, but issues tokens/credentials
A228: 224 | B228: CoreStack_InventoryFinopsReadPolicy | C228: Always attached | D228: cognito-identity:Get* | E228: cognito-identity:GetPrincipalTagAttributeMap | F228: Amazon Cognito Identity | G228: Read | H228: Read | I228: Grants permission to get the principal tags for an identity pool and provider | J228: Low | L228: Read-only
A229: 225 | B229: CoreStack_InventoryFinopsReadPolicy | C229: Always attached | D229: cognito-identity:ListIdentityPools | E229: cognito-identity:ListIdentityPools | F229: Amazon Cognito Identity | G229: List | H229: Read | I229: Grants permission to list all of the Cognito identity pools registered for your account | J229: Low | L229: Read-only
A230: 226 | B230: CoreStack_InventoryFinopsReadPolicy | C230: Always attached | D230: cognito-idp:ListUserPools | E230: cognito-idp:ListUserPools | F230: Amazon Cognito User Pools | G230: List | H230: Read | I230: Grants permission to list all user pools | J230: Low | L230: Read-only
A231: 227 | B231: CoreStack_InventoryFinopsReadPolicy | C231: Always attached | D231: datapipeline:DescribePipelines | E231: datapipeline:DescribePipelines | F231: AWS Data Pipeline | G231: Read | H231: Read | I231: Grants permission to retrieves metadata about one or more pipelines | J231: Low | L231: Read-only
A232: 228 | B232: CoreStack_InventoryFinopsReadPolicy | C232: Always attached | D232: datapipeline:GetPipelineDefinition | E232: datapipeline:GetPipelineDefinition | F232: AWS Data Pipeline | G232: Read | H232: Read | I232: Grants permission to gets the definition of the specified pipeline | J232: Medium | K232: Pipeline definitions may contain connection strings/credentials. | L232: Read-only
A233: 229 | B233: CoreStack_InventoryFinopsReadPolicy | C233: Always attached | D233: datapipeline:ListPipelines | E233: datapipeline:ListPipelines | F233: AWS Data Pipeline | G233: List | H233: Read | I233: Grants permission to list the pipeline identifiers for all active pipelines that you have permission to access | J233: Low | L233: Read-only
A234: 230 | B234: CoreStack_InventoryFinopsReadPolicy | C234: Always attached | D234: directconnect:Describe* | E234: directconnect:DescribeConnectionLoa | F234: AWS Direct Connect | G234: Read | H234: Read | I234: Grants permission to describe the LOA-CFA for a Connection | J234: Low | L234: Read-only
A235: 231 | B235: CoreStack_InventoryFinopsReadPolicy | C235: Always attached | D235: directconnect:Describe* | E235: directconnect:DescribeConnections | F235: AWS Direct Connect | G235: Read | H235: Read | I235: Grants permission to describe all connections in this region | J235: Low | L235: Read-only
A236: 232 | B236: CoreStack_InventoryFinopsReadPolicy | C236: Always attached | D236: directconnect:Describe* | E236: directconnect:DescribeConnectionsOnInterconnect | F236: AWS Direct Connect | G236: Read | H236: Read | I236: Grants permission to describe a list of connections that have been provisioned on the given interconnect | J236: Low | L236: Read-only
A237: 233 | B237: CoreStack_InventoryFinopsReadPolicy | C237: Always attached | D237: directconnect:Describe* | E237: directconnect:DescribeCustomerMetadata | F237: AWS Direct Connect | G237: Read | H237: Read | I237: Grants permission to view a list of customer agreements, along with their signed status and whether the customer is an NNIPartner, NNIPartnerV2, or a nonPartner | J237: Low | L237: Read-only
A238: 234 | B238: CoreStack_InventoryFinopsReadPolicy | C238: Always attached | D238: directconnect:Describe* | E238: directconnect:DescribeDirectConnectGatewayAssociationProposals | F238: AWS Direct Connect | G238: Read | H238: Read | I238: Grants permission to describe one or more association proposals for connection between a virtual private gateway and a Direct Connect gateway | J238: Low | L238: Read-only
A239: 235 | B239: CoreStack_InventoryFinopsReadPolicy | C239: Always attached | D239: directconnect:Describe* | E239: directconnect:DescribeDirectConnectGatewayAssociations | F239: AWS Direct Connect | G239: Read | H239: Read | I239: Grants permission to describe the associations between your Direct Connect gateways and virtual private gateways | J239: Low | L239: Read-only
A240: 236 | B240: CoreStack_InventoryFinopsReadPolicy | C240: Always attached | D240: directconnect:Describe* | E240: directconnect:DescribeDirectConnectGatewayAttachments | F240: AWS Direct Connect | G240: Read | H240: Read | I240: Grants permission to describe the attachments between your Direct Connect gateways and virtual interfaces | J240: Low | L240: Read-only
A241: 237 | B241: CoreStack_InventoryFinopsReadPolicy | C241: Always attached | D241: directconnect:Describe* | E241: directconnect:DescribeDirectConnectGateways | F241: AWS Direct Connect | G241: Read | H241: Read | I241: Grants permission to describe all your Direct Connect gateways or only the specified Direct Connect gateway | J241: Low | L241: Read-only
A242: 238 | B242: CoreStack_InventoryFinopsReadPolicy | C242: Always attached | D242: directconnect:Describe* | E242: directconnect:DescribeHostedConnections | F242: AWS Direct Connect | G242: Read | H242: Read | I242: Grants permission to describe the hosted connections that have been provisioned on the specified interconnect or link aggregation group (LAG) | J242: Low | L242: Read-only
A243: 239 | B243: CoreStack_InventoryFinopsReadPolicy | C243: Always attached | D243: directconnect:Describe* | E243: directconnect:DescribeInterconnectLoa | F243: AWS Direct Connect | G243: Read | H243: Read | I243: Grants permission to describe the LOA-CFA for an Interconnect | J243: Low | L243: Read-only
A244: 240 | B244: CoreStack_InventoryFinopsReadPolicy | C244: Always attached | D244: directconnect:Describe* | E244: directconnect:DescribeInterconnects | F244: AWS Direct Connect | G244: Read | H244: Read | I244: Grants permission to describe a list of interconnects owned by the AWS account | J244: Low | L244: Read-only
... A512: 508 | B512: CoreStack_InventoryFinopsReadPolicy | C512: Always attached | D512: ecr-public:GetRepositoryCatalogData | E512: ecr-public:GetRepositoryCatalogData | F512: Amazon Elastic Container Registry Public | G512: Read | H512: Read | I512: Grants permission to retrieve the catalog data associated with a repository | J512: Low | L512: Read-only
A513: 509 | B513: CoreStack_InventoryFinopsReadPolicy | C513: Always attached | D513: ecr:BatchGetImage | E513: ecr:BatchGetImage | F513: Amazon Elastic Container Registry | G513: Read | H513: Read | I513: Grants permission to get detailed information for specified images within a specified repository | J513: Low | K513: Returns image manifests only (layer download not granted). | L513: Read-only
A514: 510 | B514: CoreStack_InventoryFinopsReadPolicy | C514: Always attached | D514: ecr:DescribeImages | E514: ecr:DescribeImages | F514: Amazon Elastic Container Registry | G514: List | H514: Read | I514: Grants permission to get metadata about the images in a repository, including image size, image tags, and creation date | J514: Low | L514: Read-only
A515: 511 | B515: CoreStack_InventoryFinopsReadPolicy | C515: Always attached | D515: ecr:DescribeRepositories | E515: ecr:DescribeRepositories | F515: Amazon Elastic Container Registry | G515: Read | H515: Read | I515: Grants permission to describe image repositories in a registry | J515: Low | L515: Read-only
A516: 512 | B516: CoreStack_InventoryFinopsReadPolicy | C516: Always attached | D516: ecr:GetLifecyclePolicy | E516: ecr:GetLifecyclePolicy | F516: Amazon Elastic Container Registry | G516: Read | H516: Read | I516: Grants permission to retrieve the specified lifecycle policy | J516: Low | L516: Read-only
A517: 513 | B517: CoreStack_InventoryFinopsReadPolicy | C517: Always attached | D517: ecr:GetLifecyclePolicyPreview | E517: ecr:GetLifecyclePolicyPreview | F517: Amazon Elastic Container Registry | G517: Read | H517: Read | I517: Grants permission to retrieve the results of the specified lifecycle policy preview request | J517: Low | L517: Read-only
A518: 514 | B518: CoreStack_InventoryFinopsReadPolicy | C518: Always attached | D518: ecs:Describe* | E518: ecs:DescribeCapacityProviders | F518: Amazon Elastic Container Service | G518: Read | H518: Read | I518: Grants permission to describe one or more Amazon ECS capacity providers | J518: Low | L518: Read-only
A519: 515 | B519: CoreStack_InventoryFinopsReadPolicy | C519: Always attached | D519: ecs:Describe* | E519: ecs:DescribeClusters | F519: Amazon Elastic Container Service | G519: Read | H519: Read | I519: Grants permission to describes one or more of your clusters | J519: Low | L519: Read-only
A520: 516 | B520: CoreStack_InventoryFinopsReadPolicy | C520: Always attached | D520: ecs:Describe* | E520: ecs:DescribeContainerInstances | F520: Amazon Elastic Container Service | G520: Read | H520: Read | I520: Grants permission to describes Amazon ECS container instances | J520: Low | L520: Read-only
A521: 517 | B521: CoreStack_InventoryFinopsReadPolicy | C521: Always attached | D521: ecs:Describe* | E521: ecs:DescribeDaemon | F521: Amazon Elastic Container Service | G521: Read | H521: Read | I521: Grants permission to describe the specified daemon running in your cluster | J521: Low | L521: Read-only
A522: 518 | B522: CoreStack_InventoryFinopsReadPolicy | C522: Always attached | D522: ecs:Describe* | E522: ecs:DescribeDaemonDeployments | F522: Amazon Elastic Container Service | G522: Read | H522: Read | I522: Grants permission to describe one or more of your daemon deployments | J522: Low | L522: Read-only
A523: 519 | B523: CoreStack_InventoryFinopsReadPolicy | C523: Always attached | D523: ecs:Describe* | E523: ecs:DescribeDaemonRevisions | F523: Amazon Elastic Container Service | G523: Read | H523: Read | I523: Grants permission to describe one or more of your daemon revisions | J523: Low | L523: Read-only
A524: 520 | B524: CoreStack_InventoryFinopsReadPolicy | C524: Always attached | D524: ecs:Describe* | E524: ecs:DescribeDaemonTaskDefinition | F524: Amazon Elastic Container Service | G524: Read | H524: Read | I524: Grants permission to describe a daemon task definition | J524: Low | L524: Read-only
A525: 521 | B525: CoreStack_InventoryFinopsReadPolicy | C525: Always attached | D525: ecs:Describe* | E525: ecs:DescribeExpressGatewayService | F525: Amazon Elastic Container Service | G525: Read | H525: Read | I525: Grants permission to describe the specified Express Gateway service | J525: Low | L525: Read-only
... A720: 716 | B720: CoreStack_InventoryFinopsReadPolicy | C720: Always attached | D720: glue:Get* | E720: glue:GetCompletion | F720: AWS Glue | G720: Read | H720: Read | I720: Grants permission to get generated response for a completion request in Glue from AWS Q | J720: Low | L720: Read-only
A721: 717 | B721: CoreStack_InventoryFinopsReadPolicy | C721: Always attached | D721: glue:Get* | E721: glue:GetConnection | F721: AWS Glue | G721: Read | H721: Read | I721: Grants permission to retrieve a connection | J721: High | K721: Can return JDBC connection properties incl. username/password. | L721: Read-only
...

Sheet Write & Sensitive
A1: Actions classified by AWS as Write / Permissions management, plus Read actions exposing sensitive data or with side effects
A4: S.No | B4: Concrete Action | C4: Granted via (CFN permission) | D4: IAM Policy Name | E4: AWS Access Level (AWS label) | F4: Read / Write (per AWS label) | G4: Sensitivity | H4: Why it matters | I4: Recommendation | J4: Actual Behaviour (what the API really does)
A5: 1 | B5: cognito-identity:GetCredentialsForIdentity | C5: cognito-identity:Get* | D5: CoreStack_InventoryFinopsReadPolicy | E5: Read | F5: Read | G5: High | H5: Returns AWS credentials for a Cognito identity. | I5: Replace cognito-identity:Get* with GetIdentityPoolRoles (+ Describe*) so no credential/token issuing calls are granted. | J5: Read, but issues tokens/credentials
A6: 2 | B6: glue:GetConnection | C6: glue:Get* | D6: CoreStack_InventoryFinopsReadPolicy | E6: Read | F6: Read | G6: High | H6: Can return JDBC connection properties incl. username/password. | I6: AWS labels these SparkUI/Studio 'Get' calls as Permissions management/Write; functionally they are read. Replace glue:Get*/List* with the specific actions CoreStack needs (GetDatabases, GetTables, GetJobs, GetJobRuns, GetCrawlers, GetDevEndpoints, ListJobs...) and Deny GetConnection(s). | J6: Read-only
A7: 3 | B7: glue:GetConnections | C7: glue:Get* | D7: CoreStack_InventoryFinopsReadPolicy | E7: Read | F7: Read | G7: High | H7: Can return JDBC connection properties incl. username/password. | I7: AWS labels these SparkUI/Studio 'Get' calls as Permissions management/Write; functionally they are read. Replace glue:Get*/List* with the specific actions CoreStack needs (GetDatabases, GetTables, GetJobs, GetJobRuns, GetCrawlers, GetDevEndpoints, ListJobs...) and Deny GetConnection(s). | J7: Read-only
A8: 4 | B8: lambda:GetFunction | C8: lambda:Get* | D8: CoreStack_InventoryFinopsReadPolicy | E8: Read | F8: Read | G8: High | H8: Returns environment variables (may contain secrets) and a pre-signed URL to download function code. | I8: Replace lambda:Get* with GetFunctionConfiguration-less list (ListFunctions already returns memory/runtime) or explicit Deny lambda:GetFunction if code/env access not needed. | J8: Read-only
A9: 5 | B9: lightsail:GetInstanceAccessDetails | C9: lightsail:Get* | D9: CoreStack_InventoryFinopsReadPolicy | E9: Write | F9: Write | G9: High | H9: Returns temporary SSH/RDP keys to connect to Lightsail instances. AWS classifies as WRITE. | I9: Replace lightsail:Get* with explicit read actions (e.g. GetInstances, GetDisks, GetRelationalDatabases, GetLoadBalancers, GetBuckets) or add an explicit Deny for these two actions. | J9: Write-like - generates temporary SSH/RDP key pair for an instance (credential issuing)
A10: 6 | B10: lightsail:GetRelationalDatabaseMasterUserPassword | C10: lightsail:Get* | D10: CoreStack_InventoryFinopsReadPolicy | E10: Write | F10: Write | G10: High | H10: Returns the master password of a Lightsail database. AWS classifies as WRITE. | I10: Replace lightsail:Get* with explicit read actions (e.g. GetInstances, GetDisks, GetRelationalDatabases, GetLoadBalancers, GetBuckets) or add an explicit Deny for these two actions. | J10: Read-only, but returns a secret (DB master password)
A11: 7 | B11: logs:FilterLogEvents | C11: logs:FilterLogEvents | D11: CoreStack_FinOpsForAI_CloudWatchLogs | E11: Read | F11: Read | G11: High | H11: Searches raw log content from ANY log group (Resource '*'); Bedrock invocation logs may contain prompts/responses. | I11: Scope log-read actions to Bedrock/AgentCore invocation log groups (e.g. arn:aws:logs:*:*:log-group:/aws/bedrock/*) instead of Resource '*'. | J11: Read-only
A12: 8 | B12: logs:GetLogEvents | C12: logs:GetLogEvents | D12: CoreStack_InventoryFinopsReadPolicy | E12: Read | F12: Read | G12: High | H12: Reads raw log content from ANY log group (Resource '*'); logs may contain PII/prompts/secrets. | I12: Scope log-read actions to Bedrock/AgentCore invocation log groups (e.g. arn:aws:logs:*:*:log-group:/aws/bedrock/*) instead of Resource '*'. | J12: Read-only
A13: 9 | B13: sqs:ReceiveMessage | C13: sqs:ReceiveMessage | D13: CoreStack_InventoryFinopsReadPolicy | E13: Read | F13: Read | G13: High | H13: Consumes messages: hides them from real consumers for the visibility timeout and increments receive count (can trigger DLQ redrive). | I13: Remove sqs:ReceiveMessage (queue activity is available via CloudWatch metric NumberOfMessagesReceived) or scope to a CoreStack-owned queue. | J13: Changes state - hides received messages from consumers (visibility timeout)
A14: 10 | B14: ssm:GetParameter | C14: ssm:Get* | D14: CoreStack_InventoryFinopsReadPolicy | E14: Read | F14: Read | G14: High | H14: Can return SecureString parameter values (decrypted with aws/ssm key). | I14: Add explicit Deny on ssm:GetParameter, GetParameters, GetParametersByPath, GetParameterHistory, or replace ssm:Get* with the specific inventory actions needed. | J14: Read-only
A15: 11 | B15: ssm:GetParameterHistory | C15: ssm:Get* | D15: CoreStack_InventoryFinopsReadPolicy | E15: Read | F15: Read | G15: High | H15: Can return historical parameter values incl. SecureString. | I15: Add explicit Deny on ssm:GetParameter, GetParameters, GetParametersByPath, GetParameterHistory, or replace ssm:Get* with the specific inventory actions needed. | J15: Read-only
A16: 12 | B16: ssm:GetParameters | C16: ssm:Get* | D16: CoreStack_InventoryFinopsReadPolicy | E16: Read | F16: Read | G16: High | H16: Can return SecureString parameter values (decrypted with aws/ssm key). | I16: Add explicit Deny on ssm:GetParameter, GetParameters, GetParametersByPath, GetParameterHistory, or replace ssm:Get* with the specific inventory actions needed. | J16: Read-only
... A52: 48 | B52: securityhub:GetFindings | C52: securityhub:GetFindings | D52: CoreStack_InventoryFinopsReadPolicy | E52: Read | F52: Read | G52: Medium | H52: Reads security findings (vulnerability details). | I52: Not strictly needed for FinOps; remove if security findings are not displayed. | J52: Read-only

Sheet Findings
A1: Review findings from reading the CloudFormation template end-to-end
A4: # | B4: Type | C4: Finding | D4: Affected Permission(s) | E4: Recommendation
A5: 1 | B5: Overall | C5: All 13 inline policies use Effect 'Allow' with Get/List/Describe/View-style actions. No Create/Update/Delete/Put/Modify/Attach/Tag actions are granted. The role is designed as READ-ONLY. | D5: All | E5: -
A6: 2 | B6: Write-classified | C6: Although named Get/List/Describe, wildcards glue:Get*, glue:List*, lightsail:Get*, quicksight:Describe* and cognito-identity:Get* include actions AWS officially classifies as 'Write' or 'Permissions management' (see 'Write & Sensitive' sheet). | D6: glue:Get*, glue:List*, lightsail:Get*, quicksight:Describe*, cognito-identity:Get* | E6: Replace these wildcards with explicit action lists, or add explicit Deny statements.
A7: 3 | B7: Side effect | C7: sqs:ReceiveMessage is classified 'Read' but consumes messages (makes them invisible to real consumers and increments receive count, which can move messages to a DLQ). | D7: sqs:ReceiveMessage | E7: Remove; use CloudWatch SQS metrics instead.
A8: 4 | B8: Sensitive data | C8: Resource '*' log-read actions (logs:GetLogEvents, FilterLogEvents, StartQuery/GetQueryResults) allow reading content of ALL CloudWatch log groups, not only Bedrock invocation logs. | D8: logs:GetLogEvents, logs:FilterLogEvents, logs:StartQuery, logs:GetQueryResults | E8: Scope Resource to the Bedrock model-invocation log group(s).
A9: 5 | B9: Sensitive data | C9: lambda:Get* (GetFunction: env vars + code URL), ssm:Get* (SecureString parameter values), glue:Get* (GetConnection credentials), lightsail:Get* (SSH keys / DB master password) can expose secrets. | D9: lambda:Get*, ssm:Get*, glue:Get*, lightsail:Get* | E9: Narrow to explicit actions or add explicit Deny for the sensitive actions.
A10: 6 | B10: Invalid action | C10: The following entries are not valid IAM actions and grant nothing: clouddirectory:DescribeDirectories, codepipeline:List, cognito-user:Describe*, cognito-user:List*, s3:GetNotificationConfiguration, s3:HeadBucket, sheild:DescribeProtection, sheild:ListProtections. ('sheild' is a typo of 'shield'; 'cognito-user' is not a service prefix; 's3:HeadBucket' is authorized by s3:ListBucket; correct names are s3:GetBucketNotification and codepipeline:ListPipelines). | D10: clouddirectory:DescribeDirectories, codepipeline:List, cognito-user:Describe*, cognito-user:List*, s3:GetNotificationConfiguration, s3:HeadBucket, sheild:DescribeProtection, sheild:ListProtections | E10: Correct to shield:DescribeProtection, shield:ListProtections, codepipeline:ListPipelines, s3:GetBucketNotification; remove cognito-user:*, s3:HeadBucket and clouddirectory:DescribeDirectories.
A11: 7 | B11: Duplicate | C11: The following are granted in more than one policy (harmless, but redundant): apigateway:GET, bedrock:GetAgent, bedrock:GetAgentActionGroup, bedrock:GetInferenceProfile, bedrock:GetKnowledgeBase, bedrock:GetModelInvocationLoggingConfiguration, bedrock:ListAgentActionGroups, bedrock:ListAgentAliases, bedrock:ListAgentKnowledgeBases, bedrock:ListAgentVersions, bedrock:ListAgents, bedrock:ListFoundationModels, bedrock:ListTagsForResource, logs:DescribeLogGroups, logs:DescribeLogStreams. | D11: apigateway:GET, bedrock:GetAgent, bedrock:GetAgentActionGroup, bedrock:GetInferenceProfile, bedrock:GetKnowledgeBase, bedrock:GetModelInvocationLoggingConfiguration, bedrock:ListAgentActionGroups, bedrock:ListAgentAliases, bedrock:ListAgentKnowledgeBases, bedrock:ListAgentVersions, bedrock:ListAgents, bedrock:ListFoundationModels, bedrock:ListTagsForResource, logs:DescribeLogGroups, logs:DescribeLogStreams | E11: Keep once; duplication only matters for policy size limits.
A12: 8 | B12: Scope | C12: Only s3:GetObject is resource-scoped (CUR bucket). All other statements use Resource '*'. | D12: All except s3:GetObject | E12: Acceptable for account-wide inventory; consider scoping logs:* and s3:ListBucket.
A13: 9 | B13: Wildcard growth | C13: Wildcards (e.g. ec2:Describe*) automatically include any new actions AWS adds in future matching the pattern. | D13: All wildcard entries | E13: Periodically re-review, or pin explicit actions.
A14: 10 | B14: Trust | C14: Role can be assumed only by CoreStack AWS account (default 028811834831) with the agreed sts:ExternalId (confused-deputy protection); optionally MFA-enforced via EnforceMFA. | D14: sts:AssumeRole (trust policy) | E14: Keep ExternalId secret and unique per customer.
A15: 11 | B15: Naming | C15: Template description says 'ReadOnlyAccess' but the AWS managed ReadOnlyAccess policy is NOT attached; only the custom inline policies listed here are. | D15: - | E15: Description only - no action needed.
A16: 12 | B16: Cost note | C16: logs:StartQuery (Logs Insights) and S3 Storage Lens advanced metrics incur charges on the customer's bill. | D16: logs:StartQuery, S3CostOptimizationPolicy | E16: Communicate to customer.

Sheet Role, Trust & Parameters
A1: IAM Role, trust relationship, parameters and conditional policy attachment
A4: Item | B4: Value / Behaviour | C4: Description
A5: Resource created | B5: AWS::IAM::Role (name = RoleName parameter), tag Purpose=CoreStack | C5: Cross-account role that CoreStack assumes to read the customer's account.
A6: Trusted principal | B6: arn:aws:iam::<CoreStackAccountId>:root (default 028811834831) | C6: Only the CoreStack AWS account can assume this role.
A7: Trust action | B7: sts:AssumeRole | C7: Allows CoreStack to obtain temporary credentials for this role. (Granted in trust policy, not to the role itself.)
A8: Trust condition - ExternalId | B8: StringEquals sts:ExternalId = <ExternalId> | C8: Prevents the confused-deputy problem: CoreStack must present the agreed external ID.
A9: Trust condition - MFA | B9: Bool aws:MultiFactorAuthPresent = true (only if EnforceMFA = true) | C9: Optionally requires MFA on the assuming session.
A10: Outputs | B10: RoleARN, ExternalId, MFAEnabled, BedrockPermissionsEnabled, FinOpsForAIEnabled | C10: Values to be entered in CoreStack during onboarding.
A12: Parameter | B12: Default / Allowed | C12: Description (from CFN)
A13: RoleName | B13: Required | C13: The name of the IAM role to create. Use alphanumeric and '+=,.@-_' characters.
A14: ExternalId | B14: Required | C14: The external ID can be any word or number that is agreed upon between you and the third-party (Corestack - 028811834831) account. Use alphanumeric and '=,.@:/-' characters.
A15: AWSCostAndUsageReportCURBucketName | B15: Required | C15: The name of the Cost and Usage Report (CUR) S3 bucket name to get Cost details. NOTE: THIS IS AN OPTIONAL PARAMETER, SHOULD BE INCLUDED FOR AWS MANAGEMENT/LINKED/STANDARD ACCOUNTS FOR WHICH CUR IS ENABLED!!!!Use lowercase letters, numbers, periods (.), hyphens (-), and underscores (_)
A16: EnforceMFA | B16: Default: false; Allowed: true, false | C16: Flag to enforce MFA (Multi-Factor Authentication) when Assuming the role.
... A22: IAM Policy (CFN Resource) | B22: Attached When | C22: Permissions in policy
A23: CoreStack_BudgetAndBillingPolicy (BudgetAndBillingPolicy) | B23: Always attached | C23: 3
A24: CoreStack_SupportAndRIPolicy (SupportAndRIPolicy) | B24: Always attached | C24: 8
A25: CoreStack_AWSCURAccessPolicy (AWSCURAccessPolicy) | B25: Only if AWSCostAndUsageReportCURBucketName is provided | C25: 1
A26: CoreStack_ComputeOptimizerPolicy (ComputeOptimizerPolicy) | B26: Always attached | C26: 19
A27: CoreStack_InventoryFinopsReadPolicy (InventoryFinopsReadPolicy) | B27: Always attached | C27: 168
A28: CoreStack_S3CostOptimizationPolicy (S3CostOptimizationPolicy) | B28: Only if EnableS3CostSavingsRecommendation = true | C28: 2
A29: CoreStack_BedrockPermissions_Listing (BedrockPermissionsListingPolicy) | B29: Only if EnableBedrockPermissions = true | C29: 32
A30: CoreStack_BedrockPermissions_DeepGet (BedrockPermissionsDeepGetPolicy) | B30: Only if EnableBedrockPermissions = true | C30: 22
A31: CoreStack_BedrockPermissions_TagRead (BedrockPermissionsTagReadPolicy) | B31: Only if EnableBedrockPermissions = true | C31: 2
A32: CoreStack_FinOpsForAI_Bedrock (FinOpsForAIBedrockPolicy) | B32: Only if EnableFinOpsForAI = true | C32: 14
A33: CoreStack_FinOpsForAI_CloudWatchLogs (FinOpsForAICloudWatchLogsPolicy) | B33: Only if EnableFinOpsForAI = true | C33: 6
A34: CoreStack_FinOpsForAI_IAM (FinOpsForAIIAMPolicy) | B34: Only if EnableFinOpsForAI = true | C34: 2
A35: CoreStack_FinOpsForAI_APIGateway (FinOpsForAIAPIGatewayPolicy) | B35: Only if EnableFinOpsForAI = true | C35: 1

Sheet Access Level Guide
A1: How to read the AWS 'Access Level' label - and why some Get/Describe actions are labelled Write
A4: Topic | B4: Explanation
A5: What is 'Access level'? | B5: Each IAM action in the AWS Service Authorization Reference carries one of five labels: List, Read, Write, Permissions management, Tagging. AWS uses these labels in the IAM console policy summary and in tools like IAM Access Analyzer.
A6: List | B6: List resources (names/IDs) - e.g. ec2:DescribeInstances, s3:ListAllMyBuckets.
A7: Read | B7: Read contents/attributes of a resource - e.g. s3:GetObject, rds:DescribeDBInstances.
A8: Write | B8: Create, delete or modify a resource - e.g. ec2:TerminateInstances.
A9: Permissions management | B9: Grant or modify permissions on a resource - e.g. iam:PutRolePolicy, s3:PutBucketPolicy. In AWS's data these are recorded as 'Permissions management, Write' because changing a permission is also a write.
A10: Tagging | B10: Add/remove tags only.
A11: KEY POINT 1 - the label does not grant anything | B11: IAM authorizes by ACTION NAME, never by label. 'glue:GetStage' does exactly what the GetStage API does (returns Spark stage details), whatever label it carries. Changing the label would not change what CoreStack can do.
A12: KEY POINT 2 - labels are set by each service team and are sometimes inconsistent | B12: Example from QuickSight: DescribeDashboardPermissions, DescribeAnalysisPermissions and DescribeDataSetPermissions are labelled READ, but the very similar DescribeTopicPermissions, DescribeSpacePermissions and DescribeKnowledgeBasePermissions are labelled 'Permissions management, Write'. All six only return the resource policy. Likewise s3:GetBucketPolicy, kms:GetKeyPolicy, lambda:GetPolicy and glue:GetResourcePolicy (all read a policy) are labelled READ. The likely reason is that AWS tags an action by the resource area it concerns (permissions) rather than by what the call does - but AWS does not publish its reasoning.
A13: KEY POINT 3 - Glue SparkUI / Studio actions | B13: glue:GetStage, GetStages, GetQueries, GetExecutors, GetStorage etc. back the Spark UI screen in the Glue console, and GetDataPreviewStatement / GetRecipeAction / ListEntities / ListConnectionTypes back Glue Studio. They return monitoring/preview data. AWS labels them 'Permissions management, Write' although none creates or changes anything.
A14: Which Write-labelled actions actually change something? | B14: Only two of the 25: cognito-identity:GetId (can create a new identity in an identity pool) and lightsail:GetInstanceAccessDetails (generates temporary SSH keys). lightsail:GetRelationalDatabaseMasterUserPassword changes nothing but returns a password. The other 22 are functionally read-only. Separately, sqs:ReceiveMessage is labelled Read but does change message state.
A15: Why do they appear in the CFN at all? | B15: They are not listed by name. They come in through wildcards: glue:Get*, glue:List*, quicksight:Describe*, lightsail:Get*, cognito-identity:Get*. A wildcard grants every action whose name matches, including ones AWS adds later.
... A17: Source | B17: AWS Service Authorization Reference, as published in the iam-dataset project (github.com/iann0036/iam-dataset), retrieved 2026-09-28. Verify any action at https://docs.aws.amazon.com/service-authorization/latest/reference/ (e.g. list_awsglue.html, list_amazonquicksight.html).
